skill_tagging/__init__.py
skill_tagging/apps.py
skill_tagging/handlers.py
skill_tagging/pipeline.py
skill_tagging/skill_tagging_mixin.py
skill_tagging/utils.py
skill_tagging/static/brainstorming.svg
skill_tagging/static/tagging.css
skill_tagging/static/tagging.html
skill_tagging/static/tagging.js
skill_tagging/static/tags_error.html
skill_tagging/static/tags_form.html
skill_tagging/static/tags_thankyou.html
skill_tagging/static/video_tagging.js
skill_tagging-0.4.0.dist-info/AUTHORS
skill_tagging-0.4.0.dist-info/LICENSE
skill_tagging-0.4.0.dist-info/LICENSE.txt
skill_tagging-0.4.0.dist-info/METADATA
skill_tagging-0.4.0.dist-info/WHEEL
skill_tagging-0.4.0.dist-info/entry_points.txt
skill_tagging-0.4.0.dist-info/top_level.txt
skill_tagging-0.4.0.dist-info/RECORD
