Metadata-Version: 2.1
Name: skill_tagging
Version: 0.4.0
Summary: Django app plugin for fetching and verifying tags for xblock skills.
Home-page: https://github.com/openedx/xblock-skill-tagging
Author: edX
Author-email: oscm@edx.org
License: AGPL 3.0
Keywords: Python edx
Classifier: Development Status :: 3 - Alpha
Classifier: Framework :: Django
Classifier: Framework :: Django :: 4.2
Classifier: Framework :: Django :: 5.2
Classifier: Intended Audience :: Developers
Classifier: License :: OSI Approved :: GNU Affero General Public License v3 or later (AGPLv3+)
Classifier: Natural Language :: English
Classifier: Programming Language :: Python :: 3
Classifier: Programming Language :: Python :: 3.11
Classifier: Programming Language :: Python :: 3.12
Requires-Python: >=3.11
License-File: LICENSE
License-File: LICENSE.txt
License-File: AUTHORS
Requires-Dist: Django
Requires-Dist: django-model-utils
Requires-Dist: lazy
Requires-Dist: openedx-django-pyfs
Requires-Dist: openedx-filters
Requires-Dist: openedx-events
